LICENSE
LICENSE.txt
README.md
setup.cfg
setup.py
songline/__init__.py
songline/sendline.py
songline.egg-info/PKG-INFO
songline.egg-info/SOURCES.txt
songline.egg-info/dependency_links.txt
songline.egg-info/requires.txt
songline.egg-info/top_level.txt