Metadata-Version: 2.1
Name: songline
Version: 0.0.2
Summary: Send Message, Sticker ,Image to LINE
Home-page: https://github.com/UncleEngineer/songline
Download-URL: https://github.com/UncleEngineer/songline/archive/v_001.tar.gz
Author: Loong Wissawakorn (Uncle Engineer)
Author-email: loong.wissawakorn@gmail.com
License: MIT
Keywords: Python,Uncle Engineer,LINE API
Classifier: Development Status :: 3 - Alpha
Classifier: Intended Audience :: Developers
Classifier: Topic :: Software Development :: Build Tools
Classifier: License :: OSI Approved :: MIT License
Classifier: Programming Language :: Python :: 3
Classifier: Programming Language :: Python :: 3.4
Classifier: Programming Language :: Python :: 3.5
Classifier: Programming Language :: Python :: 3.6
Classifier: Programming Language :: Python :: 3.7
License-File: LICENSE
License-File: LICENSE.txt
